ah_blackjack/Deck.py
ah_blackjack/Game.py
ah_blackjack/LICENSE
ah_blackjack/Picture.py
ah_blackjack/Player.py
ah_blackjack/__init__.py
ah_blackjack/const.py
ah_blackjack/main.py
ah_blackjack/requiremenets.txt
ah_blackjack-0.1.4.dist-info/entry_points.txt
ah_blackjack-0.1.4.dist-info/WHEEL
ah_blackjack-0.1.4.dist-info/METADATA
ah_blackjack-0.1.4.dist-info/RECORD
